nais/__init__.py
nais/checker.py
nais/processor.py
nais/utils.py
nais_processor-0.0.35.dist-info/LICENSE.txt
nais_processor-0.0.35.dist-info/METADATA
nais_processor-0.0.35.dist-info/WHEEL
nais_processor-0.0.35.dist-info/top_level.txt
nais_processor-0.0.35.dist-info/RECORD
