Metadata-Version: 2.1
Name: nais-processor
Version: 0.0.35
Summary: Code to process ion spectrometer data files
Home-page: https://github.com/jlpl/nais-processor
Author: Janne Lampilahti
Author-email: janne.lampilahti@helsinki.fi
License-File: LICENSE.txt
Requires-Dist: pandas >=1.1.0
Requires-Dist: numpy >=1.19.0
Requires-Dist: matplotlib >=3.3.4
Requires-Dist: pyyaml >=5.4.1
Requires-Dist: xarray >=2023.2.0
Requires-Dist: tinydb >=4.7.0
Requires-Dist: aerosol-functions >=0.0.7
Requires-Dist: netcdf4 >=1.6.2
Requires-Dist: PyQt5 >=5.15.7
Requires-Dist: pyqtgraph >=0.13.1
